aitokencount/__init__.py
aitokencount/cli.py
aitokencount/core.py
aitokencount-0.1.1.dist-info/LICENSE
aitokencount-0.1.1.dist-info/METADATA
aitokencount-0.1.1.dist-info/WHEEL
aitokencount-0.1.1.dist-info/entry_points.txt
aitokencount-0.1.1.dist-info/top_level.txt
aitokencount-0.1.1.dist-info/RECORD
