Metadata-Version: 2.2
Name: aitokencount
Version: 0.1.1
Summary: Count AI tokens in files and directories using tiktoken
Home-page: https://github.com/harrywang/aitokencount
Author: Harry Wang
Author-email: harryjwang@gmail.com
Project-URL: Bug Tracker, https://github.com/harrywang/aitokencount/issues
Project-URL: Source Code, https://github.com/harrywang/aitokencount
Classifier: Programming Language :: Python :: 3
Classifier: License :: OSI Approved :: MIT License
Classifier: Operating System :: OS Independent
Requires-Python: >=3.6
License-File: LICENSE
Requires-Dist: tiktoken>=0.5.2
Dynamic: author
Dynamic: author-email
Dynamic: classifier
Dynamic: description
Dynamic: description-content-type
Dynamic: home-page
Dynamic: project-url
Dynamic: requires-dist
Dynamic: requires-python
Dynamic: summary
